{"dependencies":[{"name":"C:\\production\\space-app\\.babelrc","includedInParent":true,"mtime":1526838658183},{"name":"C:\\production\\space-app\\package.json","includedInParent":true,"mtime":1527452522267},{"name":"redux","loc":{"line":1,"column":32}},{"name":"./spacex","loc":{"line":2,"column":26}},{"name":"./loading","loc":{"line":3,"column":27}},{"name":"./apod","loc":{"line":4,"column":24}},{"name":"./issMembers","loc":{"line":5,"column":30}},{"name":"./issLocation","loc":{"line":6,"column":31}},{"name":"./error","loc":{"line":7,"column":25}}],"generated":{"js":"'use strict';\n\nObject.defineProperty(exports, \"__esModule\", {\n\tvalue: true\n});\n\nvar _redux = require('redux');\n\nvar _spacex = require('./spacex');\n\nvar _spacex2 = _interopRequireDefault(_spacex);\n\nvar _loading = require('./loading');\n\nvar _loading2 = _interopRequireDefault(_loading);\n\nvar _apod = require('./apod');\n\nvar _apod2 = _interopRequireDefault(_apod);\n\nvar _issMembers = require('./issMembers');\n\nvar _issMembers2 = _interopRequireDefault(_issMembers);\n\nvar _issLocation = require('./issLocation');\n\nvar _issLocation2 = _interopRequireDefault(_issLocation);\n\nvar _error = require('./error');\n\nvar _error2 = _interopRequireDefault(_error);\n\nfunction _interopRequireDefault(obj) { return obj && obj.__esModule ? obj : { default: obj }; }\n\nvar appReducer = (0, _redux.combineReducers)({\n\tspacex: _spacex2.default,\n\tapod: _apod2.default,\n\tissMembers: _issMembers2.default,\n\tissLocation: _issLocation2.default,\n\tloading: _loading2.default,\n\terror: _error2.default\n});\n\nexports.default = appReducer;","map":{"mappings":[{"generated":{"line":7,"column":0},"source":"src\\reducers\\index.js","original":{"line":1,"column":0}},{"generated":{"line":9,"column":0},"source":"src\\reducers\\index.js","original":{"line":2,"column":0}},{"generated":{"line":13,"column":0},"source":"src\\reducers\\index.js","original":{"line":3,"column":0}},{"generated":{"line":17,"column":0},"source":"src\\reducers\\index.js","original":{"line":4,"column":0}},{"generated":{"line":21,"column":0},"source":"src\\reducers\\index.js","original":{"line":5,"column":0}},{"generated":{"line":25,"column":0},"source":"src\\reducers\\index.js","original":{"line":6,"column":0}},{"generated":{"line":29,"column":0},"source":"src\\reducers\\index.js","original":{"line":7,"column":0}},{"generated":{"line":35,"column":0},"source":"src\\reducers\\index.js","original":{"line":9,"column":0}},{"name":"appReducer","generated":{"line":35,"column":4},"source":"src\\reducers\\index.js","original":{"line":9,"column":6}},{"generated":{"line":35,"column":17},"source":"src\\reducers\\index.js","original":{"line":9,"column":19}},{"generated":{"line":35,"column":45},"source":"src\\reducers\\index.js","original":{"line":9,"column":35}},{"name":"spacex","generated":{"line":36,"column":0},"source":"src\\reducers\\index.js","original":{"line":10,"column":1}},{"generated":{"line":36,"column":25},"source":"src\\reducers\\index.js","original":{"line":9,"column":35}},{"name":"apod","generated":{"line":37,"column":0},"source":"src\\reducers\\index.js","original":{"line":11,"column":1}},{"generated":{"line":37,"column":21},"source":"src\\reducers\\index.js","original":{"line":9,"column":35}},{"name":"issMembers","generated":{"line":38,"column":0},"source":"src\\reducers\\index.js","original":{"line":12,"column":1}},{"generated":{"line":38,"column":33},"source":"src\\reducers\\index.js","original":{"line":9,"column":35}},{"name":"issLocation","generated":{"line":39,"column":0},"source":"src\\reducers\\index.js","original":{"line":13,"column":1}},{"generated":{"line":39,"column":35},"source":"src\\reducers\\index.js","original":{"line":9,"column":35}},{"name":"loading","generated":{"line":40,"column":0},"source":"src\\reducers\\index.js","original":{"line":14,"column":1}},{"generated":{"line":40,"column":27},"source":"src\\reducers\\index.js","original":{"line":9,"column":35}},{"name":"error","generated":{"line":41,"column":0},"source":"src\\reducers\\index.js","original":{"line":15,"column":1}},{"generated":{"line":42,"column":0},"source":"src\\reducers\\index.js","original":{"line":9,"column":35}},{"generated":{"line":42,"column":1},"source":"src\\reducers\\index.js","original":{"line":9,"column":19}},{"generated":{"line":42,"column":2},"source":"src\\reducers\\index.js","original":{"line":9,"column":0}},{"name":"appReducer","generated":{"line":44,"column":18},"source":"src\\reducers\\index.js","original":{"line":18,"column":15}}],"sources":{"src\\reducers\\index.js":"import { combineReducers } from 'redux';\r\nimport spacexReducer from './spacex';\r\nimport loadingReducer from './loading';\r\nimport apodReducer from './apod';\r\nimport issMembersReducer from './issMembers';\r\nimport issLocationReducer from './issLocation';\r\nimport errorReducer from './error';\r\n\r\nconst appReducer = combineReducers({\r\n\tspacex: spacexReducer,\r\n\tapod: apodReducer,\r\n\tissMembers: issMembersReducer,\r\n\tissLocation: issLocationReducer,\r\n\tloading: loadingReducer,\r\n\terror: errorReducer\r\n});\r\n\r\nexport default appReducer;"},"lineCount":null}},"hash":"19b2f27229432d2106cb659b46ced351","cacheData":{"env":{}}}