{"dependencies":[{"name":"C:\\production\\space-app\\.postcssrc","includedInParent":true,"mtime":1526839146044},{"name":"_css_loader"}],"generated":{"css":".apod {\r\n\tbackground: #ebf0df;\r\n}\r\n\r\n.apod-icon {\r\n\tposition: absolute;\r\n\ttop: 50%;\r\n\tfont-size: 50px;\r\n\tcursor: pointer;\r\n}\r\n\r\n.left {\r\n\tleft: -3rem;\r\n}\r\n\r\n.right {\r\n\tright: -3rem;\r\n}\r\n\r\n\r\n\r\n.fetchingApod-enter {\r\n\topacity: 0;\r\n}\r\n\r\n.fetchingApod-enter-active {\r\n\topacity: 1;\r\n\ttransition: all 300ms ease-out;\r\n}\r\n\r\n.fetchingApod-exit {\r\n\topacity: 1;\r\n}\r\n\r\n.fetchingApod-exit-active {\r\n\topacity: 0;\r\n\ttransition: all 300ms ease-out;\r\n}","js":"\n        var reloadCSS = require('_css_loader');\n        module.hot.dispose(reloadCSS);\n        module.hot.accept(reloadCSS);\n      "},"hash":"53efe7216edfb13e7b8792a16577eeec","cacheData":{}}